find_zuercher/generate_counties.py
find_zuercher/update_jails_from_json.py
find_zuercher/zuercher_discovery.py
zuercherportal_api-2.0.1.dist-info/licenses/LICENSE
zuercherportal_api-2.0.1.dist-info/METADATA
zuercherportal_api-2.0.1.dist-info/WHEEL
zuercherportal_api-2.0.1.dist-info/top_level.txt
zuercherportal_api-2.0.1.dist-info/RECORD
