Metadata-Version: 2.4
Name: zuercherportal_api
Version: 2.0.1
Summary: Search data within Jail database for jails that use Zuercher Portal
Author-email: KumpeApps LLC <jakumpe@kumpeapps.com>
License:                     GNU GENERAL PUBLIC LICENSE
Project-URL: Homepage, https://github.com/kumpeapps/zuercherportal_api
Project-URL: Source, https://github.com/kumpeapps/zuercherportal_api
Project-URL: Bug Reports, https://github.com/kumpeapps/zuercherportal_api/issues
Classifier: Programming Language :: Python :: 3.11
Classifier: License :: OSI Approved :: GNU General Public License v3 (GPLv3)
Requires-Python: >=3.11
License-File: LICENSE
Requires-Dist: requests>=2.30
Requires-Dist: loguru>=0.7
Requires-Dist: dataclass_wizard
Dynamic: license-file
